astroscheduller/__init__.py
astroscheduller/__version__.py
astroscheduller/config.py
astroscheduller/core.py
astroscheduller/editor.py
astroscheduller/example.py
astroscheduller/info.py
astroscheduller/io.py
astroscheduller/plot.py
astroscheduller/schedule.py
astroscheduller/schedule_edit.py
astroscheduller/scheduller.py
astroscheduller/stats.py
astroscheduller/time.py
astroscheduller/utilities.py
astroscheduller/ashrel/AstroSchedullerIcon.png
astroscheduller/ashrel/README.txt
astroscheduller/ashrel/icon_PLE_primer.png
astroscheduller/ashrel/icon_PLQ_primer.png
astroscheduller/ashrel/icon_PNE_primer.png
astroscheduller/ashrel/icon_bottom_primer.png
astroscheduller/ashrel/icon_busy_primer.png
astroscheduller/ashrel/icon_down_primer.png
astroscheduller/ashrel/icon_error_primer.png
astroscheduller/ashrel/icon_idle_primer.png
astroscheduller/ashrel/icon_info_primer.png
astroscheduller/ashrel/icon_minus_primer.png
astroscheduller/ashrel/icon_plot_primer.png
astroscheduller/ashrel/icon_plus_primer.png
astroscheduller/ashrel/icon_running_primer.png
astroscheduller/ashrel/icon_schedule_primer.png
astroscheduller/ashrel/icon_success_primer.png
astroscheduller/ashrel/icon_top_primer.png
astroscheduller/ashrel/icon_up_primer.png
astroscheduller/interfaces/__init__.py
astroscheduller/interfaces/_funcs.py
astroscheduller/interfaces/_srcs.py
astroscheduller/interfaces/_structs.py
astroscheduller/interfaces/actions.py
astroscheduller/interfaces/add_object.py
astroscheduller/interfaces/events.py
astroscheduller/interfaces/file_actions.py
astroscheduller/interfaces/get_schedule.py
astroscheduller/interfaces/help.py
astroscheduller/interfaces/main.py
astroscheduller/interfaces/object_info.py
astroscheduller/interfaces/settings.py
astroscheduller/interfaces/tasks.py
AstroScheduller-1.0.3.2210.dist-info/LICENSE
AstroScheduller-1.0.3.2210.dist-info/METADATA
AstroScheduller-1.0.3.2210.dist-info/WHEEL
AstroScheduller-1.0.3.2210.dist-info/top_level.txt
AstroScheduller-1.0.3.2210.dist-info/RECORD
