Metadata-Version: 2.1
Name: AstroScheduller
Version: 1.0.3.2210
Summary: AstroScheduller algorithms and packages for planning astronomical observations.
Home-page: https://github.com/AstroScheduller/AstroScheduller
Author: Wenky
Author-email: wxia1@fandm.edu
License: UNKNOWN
Platform: UNKNOWN
License-File: LICENSE
Requires-Dist: numpy
Requires-Dist: matplotlib
Requires-Dist: requests
Requires-Dist: astropy
Requires-Dist: Pillow
